ctadl_networkx_export_plugin/VERSION
ctadl_networkx_export_plugin/__init__.py
ctadl_networkx_export_plugin-0.0.1.dist-info/LICENSE.txt
ctadl_networkx_export_plugin-0.0.1.dist-info/METADATA
ctadl_networkx_export_plugin-0.0.1.dist-info/WHEEL
ctadl_networkx_export_plugin-0.0.1.dist-info/top_level.txt
ctadl_networkx_export_plugin-0.0.1.dist-info/RECORD
