Metadata-Version: 2.1
Name: ctadl-networkx-export-plugin
Version: 0.0.1
Summary: Exports the CTADL database to networkx format
Home-page: https://github.com/sandialabs/ctadl
Project-URL: Bug Tracker, https://github.com/sandialabs/ctadl/issues
Classifier: Programming Language :: Python :: 3.9
Classifier: Environment :: Console
Classifier: Environment :: Plugins
Classifier: License :: OSI Approved :: Apache Software License
Classifier: Operating System :: POSIX
Requires-Python: >=3.9
License-File: LICENSE.txt
Requires-Dist: networkx (>=2.8.6)
